labelImgPlusPlus.py
libs/__init__.py
libs/resources.py
libs/core/__init__.py
libs/core/commands.py
libs/core/settings.py
libs/core/shape.py
libs/formats/__init__.py
libs/formats/create_ml_io.py
libs/formats/labelFile.py
libs/formats/pascal_voc_io.py
libs/formats/yolo_io.py
libs/utils/__init__.py
libs/utils/constants.py
libs/utils/hashableQListWidgetItem.py
libs/utils/stringBundle.py
libs/utils/styles.py
libs/utils/ustr.py
libs/utils/utils.py
libs/widgets/__init__.py
libs/widgets/canvas.py
libs/widgets/colorDialog.py
libs/widgets/combobox.py
libs/widgets/default_label_combobox.py
libs/widgets/galleryWidget.py
libs/widgets/labelDialog.py
libs/widgets/lightWidget.py
libs/widgets/statsWidget.py
libs/widgets/toolBar.py
libs/widgets/zoomWidget.py
labelimgplusplus-2.1.0a1.dist-info/LICENSE
labelimgplusplus-2.1.0a1.dist-info/METADATA
labelimgplusplus-2.1.0a1.dist-info/WHEEL
labelimgplusplus-2.1.0a1.dist-info/entry_points.txt
labelimgplusplus-2.1.0a1.dist-info/top_level.txt
labelimgplusplus-2.1.0a1.dist-info/RECORD
