Metadata-Version: 2.1
Name: labelimgplusplus
Version: 2.1.0a1
Summary: labelImg++ is an enhanced graphical image annotation tool with Gallery Mode for browsing and labeling images
Author-email: Abhik Sarkar <abhiksark@gmail.com>
License: Copyright (c) <2015-Present> Tzutalin
Project-URL: Homepage, https://github.com/abhiksark/labelImg-plus-plus
Project-URL: Repository, https://github.com/abhiksark/labelImg-plus-plus
Keywords: labelImg,labelImgPlusPlus,annotation,deeplearning,image-annotation,bounding-box,gallery
Classifier: Development Status :: 3 - Alpha
Classifier: Intended Audience :: Developers
Classifier: Intended Audience :: Science/Research
Classifier: Natural Language :: English
Classifier: Programming Language :: Python :: 3
Classifier: Programming Language :: Python :: 3.6
Classifier: Programming Language :: Python :: 3.7
Classifier: Programming Language :: Python :: 3.8
Classifier: Programming Language :: Python :: 3.9
Classifier: Programming Language :: Python :: 3.10
Classifier: Programming Language :: Python :: 3.11
Classifier: Topic :: Scientific/Engineering :: Artificial Intelligence
Classifier: Topic :: Scientific/Engineering :: Image Recognition
Requires-Python: >=3.6
License-File: LICENSE
Requires-Dist: pyqt5
Requires-Dist: lxml
